{
  "creds": {
    "noiseKey": {
      "private": {
        "type": "Buffer",
        "data": "2POgz4FTSPbv/rwg6N86Jff+proOqCwzP5vqbQ1y0Vc="
      },
      "public": {
        "type": "Buffer",
        "data": "GvUwnL8WRfaXXK+Fbj9sYLcxrBG3yj5WzRF1WGBERzo="
      }
    },
    "signedIdentityKey": {
      "private": {
        "type": "Buffer",
        "data": "EHy89x6FmUPRJYkHTaIDYDiGll4RH2WZg2eLjXNN+lo="
      },
      "public": {
        "type": "Buffer",
        "data": "3vfeLZnYkal5s6LPyeS5P1iUxRplNwl52TMHGCI9TAQ="
      }
    },
    "signedPreKey": {
      "keyPair": {
        "private": {
          "type": "Buffer",
          "data": "2IlkWNuLIS6I/6MwS4MpogQ0stqrXzuan5Jx5asuc2U="
        },
        "public": {
          "type": "Buffer",
          "data": "v6Gi5B5tw/zRzIcQrrA14m1QOPyA/kBBf2NIUcddGGY="
        }
      },
      "signature": {
        "type": "Buffer",
        "data": "O9lEnkLxSSzVNtmitq1kaB8d+c74VKxMyPldpi6dMVO5O1n4Kjv+ypOccWxPtz/vhw9nQ3ph926JwRjPzvcEjw=="
      },
      "keyId": 1
    },
    "registrationId": 158,
    "advSecretKey": "mP3cAi0uOULgz36hKeuarGL73VTYzW78uKvVVOY873k=",
    "processedHistoryMessages": [
      {
        "key": {
          "remoteJid": "6285879528348@s.whatsapp.net",
          "fromMe": true,
          "id": "3D006C670766F16F3F6F2D9C87972280"
        },
        "timestamp": 1656310832
      },
      {
        "key": {
          "remoteJid": "6285879528348@s.whatsapp.net",
          "fromMe": true,
          "id": "83D3AD02EAE7D98A76F9EAF12C708CC3"
        },
        "timestamp": 1656310832
      },
      {
        "key": {
          "remoteJid": "6285879528348@s.whatsapp.net",
          "fromMe": true,
          "id": "A6322C47AADB23E6AA46BED45BF0AD15"
        },
        "timestamp": 1656310852
      }
    ],
    "nextPreKeyId": 31,
    "firstUnuploadedPreKeyId": 31,
    "accountSettings": {
      "unarchiveChats": false
    },
    "account": {
      "details": "CO6/tPQGEKmY5ZUGGAQ=",
      "accountSignature": "SVSK/NGxHqI3Aiklb5AE0iSzrvzT4CH/ASN7FQ9ENOhCcwEz1A6OJYID5UoNoFrcLj0BNk9cDS4xIAHJnXdBAA==",
      "deviceSignature": "SWN1Kcxc7JjhBFRwutXIzxoRVnBRvYtr5DFwDLGvgT3/B7C0GbCCeKSVJLiVP13Xr9dRbO2jWz93CDtNx71HiA=="
    },
    "me": {
      "id": "6285879528348:27@s.whatsapp.net",
      "name": "HitoBotzメ",
      "jid": "6285879528348@s.whatsapp.net"
    },
    "signalIdentities": [
      {
        "identifier": {
          "name": "6285879528348:27@s.whatsapp.net",
          "deviceId": 0
        },
        "identifierKey": {
          "type": "Buffer",
          "data": "BTbooWvZKsMKCRZE7FKMgFEp9rlc6tEm1EM5S1GLFyxX"
        }
      }
    ],
    "platform": "android",
    "lastAccountSyncTimestamp": 1656310829,
    "myAppStateKeyId": "AAAAAKkg"
  },
  "keys": {
    "preKeys": {
      "1": {
        "private": {
          "type": "Buffer",
          "data": "oBz3Fej/vYL9ChGG9VT2Y8r7AhhOcnXHvWppLbuEGm0="
        },
        "public": {
          "type": "Buffer",
          "data": "4JWMS893e3hT/jaOT0DVR+at7aX9aV13lK3MTsdzfzg="
        }
      },
      "2": {
        "private": {
          "type": "Buffer",
          "data": "4HE2DMGUa/ux2w96IFYkoWFdnrf+K0uslYBnw2Um70o="
        },
        "public": {
          "type": "Buffer",
          "data": "BUmiVKebLqhUe8WhljkXTGXfYTGTl9p6rQHuD6yuTiA="
        }
      },
      "3": {
        "private": {
          "type": "Buffer",
          "data": "ED6FAhZt0BEHdCIrFgCyHBt0RwWrGhLVhRGspaT8YnU="
        },
        "public": {
          "type": "Buffer",
          "data": "Mwjeg/Ma5DuZOrZBVu4dxoZesAdbqVoU2obBAyx+wB8="
        }
      },
      "4": null,
      "5": {
        "private": {
          "type": "Buffer",
          "data": "aFrIzSCY50caLMVR8dVf05jq6+Tbs7nxDB1B7p0FunI="
        },
        "public": {
          "type": "Buffer",
          "data": "GyMCRfUXp8MWaAkN+d/4xJTsqTO8wqbpYYJx0OyAqnM="
        }
      },
      "6": {
        "private": {
          "type": "Buffer",
          "data": "4I1Z3goIMFwMKrSUiPgUb7pCTFwI1yeFjGVgM5jTPG8="
        },
        "public": {
          "type": "Buffer",
          "data": "1YKAGlDVP4Fl2iddgNDRKPtvF+gfR65l/Y5dCQUkhXU="
        }
      },
      "7": {
        "private": {
          "type": "Buffer",
          "data": "MLEU6bBptyKKQYhpjsbrwXrA8piyoeVIIDjchN7wzEU="
        },
        "public": {
          "type": "Buffer",
          "data": "TyaxAIGR+KTnnoofdUg8MavyHF7i8C9Y+Olc3GKuwWI="
        }
      },
      "8": {
        "private": {
          "type": "Buffer",
          "data": "CIlFGWQfrWv82Q+1AZthhrP/GNpaYz4/me7dPkJvCU0="
        },
        "public": {
          "type": "Buffer",
          "data": "H3aZ6MN9BMqG7bOKTDaD8pwJ5dqMY9wcnlS5mM+rxTc="
        }
      },
      "9": {
        "private": {
          "type": "Buffer",
          "data": "EAwWzp2qRfYbcTnyg2j1hZrbutbi47o7Qxy6k82wyk8="
        },
        "public": {
          "type": "Buffer",
          "data": "wxkoLPm7kJspEs+6if8FpSW4sgz8QgKfU/YCQocBoD4="
        }
      },
      "10": {
        "private": {
          "type": "Buffer",
          "data": "gILlOV0SCHc7nJ5SOx4o7NtQEzgZnwBetXEVDtjNaU0="
        },
        "public": {
          "type": "Buffer",
          "data": "8JGQzzgioh41/V211PwTbRwqfruFmzQZhfFGXGELvRI="
        }
      },
      "11": {
        "private": {
          "type": "Buffer",
          "data": "iKLbRnvBocUcFXrBnEL4vqF0QaQqSbJ3RqY5VCAp9W8="
        },
        "public": {
          "type": "Buffer",
          "data": "znrLDFRSxOZ7DTFh6cED0aOjOkJ9TD1l8tubyqX4a3M="
        }
      },
      "12": {
        "private": {
          "type": "Buffer",
          "data": "kBI8jV402AdwQzx+HH19zIOhv1vD/4vpr/8UhIyRnEU="
        },
        "public": {
          "type": "Buffer",
          "data": "ffMmQTqclJACG7BJiQBFwCJ/r3xHgIv4Ez9lW+l+oVM="
        }
      },
      "13": {
        "private": {
          "type": "Buffer",
          "data": "6DzpJzwl7B45MDrV1s23I6IxKid5rzCGn49GPfy5CUQ="
        },
        "public": {
          "type": "Buffer",
          "data": "9azsUCTJa+kW3FXqHl3QIJMMuFKv60EBsCPZ+maKuxY="
        }
      },
      "14": {
        "private": {
          "type": "Buffer",
          "data": "GLUK1aZnuI405W5FpLh2QpnIBjhC97SytHIqJALAnGc="
        },
        "public": {
          "type": "Buffer",
          "data": "QtK8PLd/E4vr/vO0dsFQTAMbX4Ubshtl1croxfq2Gxc="
        }
      },
      "15": {
        "private": {
          "type": "Buffer",
          "data": "YIYndTTlLhmNzq5LYuNGCstF63AQcTKUfohrw7Fztkw="
        },
        "public": {
          "type": "Buffer",
          "data": "aKvmMlUZ0j8BC4Qjermg/JQ7lRT0lB6RaYqsWjTDAzc="
        }
      },
      "16": {
        "private": {
          "type": "Buffer",
          "data": "KKVMytgx+ryxoiDpXMZWfjXty0QGAEaz/b5cLlpuwGo="
        },
        "public": {
          "type": "Buffer",
          "data": "kNby7pt4fRS4OaqrV12HQm6dG/ICv0bTDe9k9aGB2UQ="
        }
      },
      "17": {
        "private": {
          "type": "Buffer",
          "data": "kNoqIAGL4LK5470tIxC6UTD5cdMFwSFdc+WQEy9fdkA="
        },
        "public": {
          "type": "Buffer",
          "data": "54orgWeFxkQ2gRvEwLBHtDadpHWv+3D/AixKHtlBj3w="
        }
      },
      "18": {
        "private": {
          "type": "Buffer",
          "data": "0KRt1LC/LuoqzoIV8bGx6RXR4WcBnpO60ampgn+nGmA="
        },
        "public": {
          "type": "Buffer",
          "data": "9ejH6nr6d+TDO4/8d6tjJBV9ef/CL/1BedV2O/LmiBo="
        }
      },
      "19": {
        "private": {
          "type": "Buffer",
          "data": "gH9vZGRYEb2Z1GgqO+8vgGEwgT5AsfKshUD0Th+3m2I="
        },
        "public": {
          "type": "Buffer",
          "data": "11Jvms9hLSzuwhEEIsWkh+GV6iGiAIm/qboa2ooFUWs="
        }
      },
      "20": {
        "private": {
          "type": "Buffer",
          "data": "MHW9Tq5UTJe8unW5OFq3D/xbJgxw5kkGospO8dN2gE4="
        },
        "public": {
          "type": "Buffer",
          "data": "bGt87XXSv+V4nzRdRB6s2QiaDt3B4P9195nDfzzgmg4="
        }
      },
      "21": {
        "private": {
          "type": "Buffer",
          "data": "uCJ13sW/CDPZx44C6q5bSGu259Ocg46D3mjWLZ8Ua2w="
        },
        "public": {
          "type": "Buffer",
          "data": "d3nVQPc09G/H8morZDyXpaYMUoTuWyIDU2LFs0FI/TE="
        }
      },
      "22": {
        "private": {
          "type": "Buffer",
          "data": "wPFWkhauragfxjhxANtBZ9kZNnsBVd+g6DejHhSSp24="
        },
        "public": {
          "type": "Buffer",
          "data": "JlGsfkY+m2A5ttNZf9oijlytQO/r4GzV4T52sxXK4TE="
        }
      },
      "23": {
        "private": {
          "type": "Buffer",
          "data": "GNDbjVwJaMKc2gbhZHbIb0ivw3kXJBK2kbSpqUcwVEE="
        },
        "public": {
          "type": "Buffer",
          "data": "N3/25A4tYSFHqvOrIRU3NFem8HhszHkIk9v2uP0zPiI="
        }
      },
      "24": {
        "private": {
          "type": "Buffer",
          "data": "wHGatM7UQDb3HAvttJA1imlmKF2Mkw3ZoM3M/0mK41E="
        },
        "public": {
          "type": "Buffer",
          "data": "wk390QCbvc8zkorPhP9N9bS59SlEChoEC4Pzox74qh0="
        }
      },
      "25": {
        "private": {
          "type": "Buffer",
          "data": "mJoZpTXrMG0daUr7OsP/CKMT+11J/RQ/iPfRzzlubUs="
        },
        "public": {
          "type": "Buffer",
          "data": "WW3HDFJfpkcR7xrm+1AtdBrdTG4z6NH6I3AXfpKedms="
        }
      },
      "26": {
        "private": {
          "type": "Buffer",
          "data": "2CzJ3wHz0KjhguZcx7g9MKuTdBcpoKckycGQcxJexU0="
        },
        "public": {
          "type": "Buffer",
          "data": "93eiOImICuqrFasQM/SL6Z8NxVlXkr58nIXXH6ra1VY="
        }
      },
      "27": {
        "private": {
          "type": "Buffer",
          "data": "qGQPQEb08ip93PNq/RsFczNbDVcHVnaBPLM4WWS8qk4="
        },
        "public": {
          "type": "Buffer",
          "data": "3QWbmuLxkr18aBi/W6/sStSp2GNbM+dNQCj4bV2PO2o="
        }
      },
      "28": {
        "private": {
          "type": "Buffer",
          "data": "cPt0Ae5Zv8zdHlhaZ3OtGQsGpn45GChXWqrkAjJ4Nks="
        },
        "public": {
          "type": "Buffer",
          "data": "Z+Mx4LXEKd1jf84ZGMszsO9WV9ovq75A8BqlSJ9gqXg="
        }
      },
      "29": {
        "private": {
          "type": "Buffer",
          "data": "oMaE+72RZMQNrQhsCQAr4OF+6bVANQSXJVSoeyOuEUU="
        },
        "public": {
          "type": "Buffer",
          "data": "7jmIWQqWl4O3Az5XLkpXtb2oGmM5ef3a4gz8UlX40CQ="
        }
      },
      "30": {
        "private": {
          "type": "Buffer",
          "data": "WKYuJ84VUVsMCY5l0lY+4LfBvXlGavkf3a+4bNYHKHs="
        },
        "public": {
          "type": "Buffer",
          "data": "6LoUSX4wU2zCgaI9NOFvV75/LjNmKdIfzMBgc7YQqXM="
        }
      }
    },
    "sessions": {
      "6285879528348.0": {
        "_sessions": {
          "BQudGo6SFoFytugb0Gp66Iq/vRz4KEgFlnHQOLc0U3d5": {
            "registrationId": 338953272,
            "currentRatchet": {
              "ephemeralKeyPair": {
                "pubKey": "BVyVEpP42wJlk66N6XENJdV2rdZaY3/8MYfy5TRwFSk7",
                "privKey": "yFRjAqseZpXwZC6kNr7QGRyr+Z+3nVu75yFDLnVGxk8="
              },
              "lastRemoteEphemeralKey": "Bex4q6MnWlid6XbgV2UiJONKtYXp8bH9+Zl8PhJpM0wz",
              "previousCounter": 0,
              "rootKey": "GG/IzipgyAs3V0VDJIKcEKga6zlJi9izbVuwdQgrX0k="
            },
            "indexInfo": {
              "baseKey": "BQudGo6SFoFytugb0Gp66Iq/vRz4KEgFlnHQOLc0U3d5",
              "baseKeyType": 2,
              "closed": -1,
              "used": 1656310830541,
              "created": 1656310830541,
              "remoteIdentityKey": "BTbooWvZKsMKCRZE7FKMgFEp9rlc6tEm1EM5S1GLFyxX"
            },
            "_chains": {
              "Bex4q6MnWlid6XbgV2UiJONKtYXp8bH9+Zl8PhJpM0wz": {
                "chainKey": {
                  "counter": 6,
                  "key": "nOa9ISX/pDxnajJhR4xa6a8CI/8PR8T29MrW2z3wo84="
                },
                "chainType": 2,
                "messageKeys": {}
              },
              "BVyVEpP42wJlk66N6XENJdV2rdZaY3/8MYfy5TRwFSk7": {
                "chainKey": {
                  "counter": 2,
                  "key": "4djrpkiH2utrSxLQKdMuvl/kkVEbPbxKsBNkVzZrack="
                },
                "chainType": 1,
                "messageKeys": {}
              }
            }
          }
        },
        "version": "v1"
      },
      "6285740392651.0": {
        "_sessions": {
          "BZPQ7SWZPYWkg7n1qCjc5BjRzh5VA8jhGPWHXLCTARYF": {
            "registrationId": 1454224371,
            "currentRatchet": {
              "ephemeralKeyPair": {
                "pubKey": "BfZKdDq4YG52Y4FeXVRRnUYG4Sp0ttXX+AYbcv+dJKwL",
                "privKey": "SJyh0acZPVi2zDN95F78Z9QRgrfXUrlD4Q5FXJXhFm8="
              },
              "lastRemoteEphemeralKey": "BaLfwkgTb5XZP9v8+lhURkJzPu88fhslbaIzoTr0Y0tF",
              "previousCounter": 0,
              "rootKey": "k0QdJrKaGx1eTeMKjinYjc3mscuC2KbfwneujzMvlN0="
            },
            "indexInfo": {
              "baseKey": "BZPQ7SWZPYWkg7n1qCjc5BjRzh5VA8jhGPWHXLCTARYF",
              "baseKeyType": 2,
              "closed": -1,
              "used": 1656310899121,
              "created": 1656310889192,
              "remoteIdentityKey": "BTmAjMrA96ux1JsNk50oUFaSpIndMqjOm7sT6Lcp84d+"
            },
            "_chains": {
              "Bd1qS1+E8nn9XuxhpDbS5PyArt9h3s0TDf6BOlXQ1ron": {
                "chainKey": {
                  "counter": 0
                },
                "chainType": 2,
                "messageKeys": {}
              },
              "BaLfwkgTb5XZP9v8+lhURkJzPu88fhslbaIzoTr0Y0tF": {
                "chainKey": {
                  "counter": 0,
                  "key": "H994mxM/Ckaw/5ohso7SMDYCzpk22ngtIsH8Zh2zAGk="
                },
                "chainType": 2,
                "messageKeys": {}
              },
              "BfZKdDq4YG52Y4FeXVRRnUYG4Sp0ttXX+AYbcv+dJKwL": {
                "chainKey": {
                  "counter": 1,
                  "key": "CP4YdcQpK46cwdrztLrgISh2tY/kYqGy6Do4Dr3exDg="
                },
                "chainType": 1,
                "messageKeys": {}
              }
            }
          }
        },
        "version": "v1"
      },
      "6285879528348:24.0": {
        "_sessions": {
          "BUkfXps1j/8boPTOZLkzb6eWy9RaZ2MewS0DkGj4DJgH": {
            "registrationId": 117,
            "currentRatchet": {
              "ephemeralKeyPair": {
                "pubKey": "BeIuseSfgRN4z2AZ/2RutfO06iujepEZvg1HmwJ17C8n",
                "privKey": "oHDkPcnLqQ8rsyv38vXeUlg7JyFzBgzESwTgNNhHL34="
              },
              "lastRemoteEphemeralKey": "BQ4MNOCijeRWwWP+nspyw8zB9NqOConAv3UTQDllpgQy",
              "previousCounter": 0,
              "rootKey": "K+Nm8RhqakBvhqxk4DJRi1ObJjJCR+PWVOU97SzeLUM="
            },
            "indexInfo": {
              "baseKey": "BUkfXps1j/8boPTOZLkzb6eWy9RaZ2MewS0DkGj4DJgH",
              "baseKeyType": 1,
              "closed": -1,
              "used": 1656310891362,
              "created": 1656310891362,
              "remoteIdentityKey": "BeT+5vqaEdN415hCwV28t+rH46hzHZepfpRe1UMWKqAd"
            },
            "_chains": {
              "BeIuseSfgRN4z2AZ/2RutfO06iujepEZvg1HmwJ17C8n": {
                "chainKey": {
                  "counter": 2,
                  "key": "lC+TXO+qRhBVqfL4LtK7qA2MTHXrUpcScfqD1wf4ejo="
                },
                "chainType": 1,
                "messageKeys": {}
              }
            },
            "pendingPreKey": {
              "signedKeyId": 1,
              "baseKey": "BUkfXps1j/8boPTOZLkzb6eWy9RaZ2MewS0DkGj4DJgH"
            }
          }
        },
        "version": "v1"
      },
      "6285879528348:25.0": {
        "_sessions": {
          "BVwa2RWOGk3SUavKrHldRdUF13S/XKelxUFVZTc67oEd": {
            "registrationId": 14,
            "currentRatchet": {
              "ephemeralKeyPair": {
                "pubKey": "BRiEpF7xo5zzQhS1IWqyQnOH6kG/7WklL34yGGt0IJko",
                "privKey": "0PygKnp01KNkbl4U39Wo0dZSNtCE0pL35DAgK0BytX8="
              },
              "lastRemoteEphemeralKey": "BYkDcf3BOPGZgDJijFNskhN9V+pcK9x2+rN02Q6uFMho",
              "previousCounter": 0,
              "rootKey": "TVIZJ3mMQxVMeUSfk+vL9trNODw04UN38KyANklWN+M="
            },
            "indexInfo": {
              "baseKey": "BVwa2RWOGk3SUavKrHldRdUF13S/XKelxUFVZTc67oEd",
              "baseKeyType": 1,
              "closed": -1,
              "used": 1656310891410,
              "created": 1656310891410,
              "remoteIdentityKey": "BVMsD/9vcPRxKcSzscJC4O7C9a2NhSaZTFNZTUc+MuBN"
            },
            "_chains": {
              "BRiEpF7xo5zzQhS1IWqyQnOH6kG/7WklL34yGGt0IJko": {
                "chainKey": {
                  "counter": 2,
                  "key": "Uk0SJ7tlu/dRU9TQMQ6NuuIFld/zzyWoV2Ad2sFumQ8="
                },
                "chainType": 1,
                "messageKeys": {}
              }
            },
            "pendingPreKey": {
              "signedKeyId": 1,
              "baseKey": "BVwa2RWOGk3SUavKrHldRdUF13S/XKelxUFVZTc67oEd"
            }
          }
        },
        "version": "v1"
      },
      "6285879528348:26.0": {
        "_sessions": {
          "BTDZj7yTyJsEnwEvPmfFQZ/bgKhGaVkG63OSu16qLOp7": {
            "registrationId": 233,
            "currentRatchet": {
              "ephemeralKeyPair": {
                "pubKey": "BZ+iTepgT7Jss1lmC7QfffLU5zATppd7i52IN4sAznZ4",
                "privKey": "mDN+Z7UApJ3A45vnRQ3vEJals65FO73cwRa9ctdfC2o="
              },
              "lastRemoteEphemeralKey": "BfexP9fap1WVo9oNDgfbbyNKexvLqaG/JYyO+T2D/6Fv",
              "previousCounter": 0,
              "rootKey": "wP4V0fZoC/DQ3uvTWGYuLBMc8NnaLTdUxKho0AQQJ9k="
            },
            "indexInfo": {
              "baseKey": "BTDZj7yTyJsEnwEvPmfFQZ/bgKhGaVkG63OSu16qLOp7",
              "baseKeyType": 1,
              "closed": -1,
              "used": 1656310891473,
              "created": 1656310891473,
              "remoteIdentityKey": "BUxcyXWtNrsrZ91MOViKR7lF+syy1lMjwBP7cW2Rl414"
            },
            "_chains": {
              "BZ+iTepgT7Jss1lmC7QfffLU5zATppd7i52IN4sAznZ4": {
                "chainKey": {
                  "counter": 2,
                  "key": "twYY7Lb+GNUrRh5VJIv/391ThTul+cuoN7LxRr72X08="
                },
                "chainType": 1,
                "messageKeys": {}
              }
            },
            "pendingPreKey": {
              "signedKeyId": 1,
              "baseKey": "BTDZj7yTyJsEnwEvPmfFQZ/bgKhGaVkG63OSu16qLOp7",
              "preKeyId": 35
            }
          }
        },
        "version": "v1"
      }
    },
    "appStateSyncKeys": {
      "AAAAAKkg": {
        "keyData": "c/RGDepUrKWH71iPdEFOpgu4zg3Njrf1sJT5oaIQHkA=",
        "fingerprint": {
          "rawId": 1854742510,
          "currentIndex": 1,
          "deviceIndexes": [
            0,
            1
          ]
        },
        "timestamp": "1655954473959"
      }
    },
    "appStateVersions": {
      "regular_low": {
        "version": 2,
        "hash": {
          "type": "Buffer",
          "data": "f/oXyHkiYenZE13JhvtWCUV4f0OPH8xeyhV+Ea6JyEDdM6zO2BFzuTfHXZu/WTAdmP1uoIvuj4QUXe7fpQR/kH5YnpN02kIsKR4VpYbjDxFXCy41S/eWSp6Bul03OXDuTgxyV9coHjnKeiRxKWmjPOUA8nWt9879Nx0aoLv34oI="
        },
        "indexValueMap": {
          "jFsvysnMtB0SZWNIXSNmxfiYIRxXaD251lU/dIvJK8Q=": {
            "valueMac": {
              "type": "Buffer",
              "data": "L7r7+5wbnDkZgesxBHu1gzRVToFTvy3UwDrGEh//9Nc="
            }
          },
          "h/6doTp9J7rgULCwPor9XJvwM+JB2cJQbSdA+rVT59g=": {
            "valueMac": {
              "type": "Buffer",
              "data": "7931MpaJ1WLmbhJYkFFB6MIJ1pkcNQdDKXJk4vIa0E8="
            }
          }
        }
      },
      "critical_block": {
        "version": 1,
        "hash": {
          "type": "Buffer",
          "data": "WDVMyWV4ajN3MdhjDxUdym/t1JGh8MfjtERB98qhlnxVz0i75+L/x0Jskk7BzX/tejcmoEc05Kn3cB/MxqScsIdykqiWIfVMX24rllPjevY2yGEKMGc7q8iELRNSrE0soRY+d25qW4BYLyQFsYEr4Hll5E+qfLZX+CgGAINIaIs="
        },
        "indexValueMap": {
          "WUo27O0+R2U7IBd+cNwA8Z4BSPC7W3Ba/5LCo24avqs=": {
            "valueMac": {
              "type": "Buffer",
              "data": "ag4V3jw6d+huvlLXj05mxoHZ+2GliYO5x4mXm48jwAU="
            }
          },
          "ljVqnW5q+T1crSPm0CBtJTt0arAB8szjbrluOBw0PZc=": {
            "valueMac": {
              "type": "Buffer",
              "data": "5ZoOK1y/AhUdMhul73PpIpP9sCErCbTzTGfI1Wajmx4="
            }
          }
        }
      },
      "regular": {
        "version": 1,
        "hash": {
          "type": "Buffer",
          "data": "Rm/yu2bmjO5DPOOfQjJRCmbFLTuUCLOVdLhZ50cixP0g2ilgljM+hFJx39VomYYh+kaHwBwbABBaW72jc2D2uqilHqfarNGlFuoC1eIqGwEcoQgALME6yazRcWkDna9OFNq+KO7dym3PCX/uC7yUnNR9by7t2BBbmxKpopkKIXA="
        },
        "indexValueMap": {
          "55U2xTK/ZZM+2pKxvisK7ZWM7qUXnPANU9CJHyXTkdI=": {
            "valueMac": {
              "type": "Buffer",
              "data": "z1He8uIs7LN55zT+G6wFeYUdEhVY8wnzulQJVX6/p68="
            }
          }
        }
      },
      "critical_unblock_low": {
        "version": 14,
        "hash": {
          "type": "Buffer",
          "data": "1hMMBksOyivpG8jwd13lImlOVEhkvwN7TGFa/gDaUF/R/E71EWY84lWy6c6b7ir9SfX4J9OCCiuT6LInNei6E7t4yV2ETxl2OdpQ3XcS8dehj5j6u8Y3XRIzTQpyqyYhIHpvf2GP1/HLGP5jf1dum4GGNDlYpHlZa/b4+tEUb+A="
        },
        "indexValueMap": {
          "AdqXvigoIxZpNP7FsTt8Wf+cavLSIcUWNiXt+tPgjO8=": {
            "valueMac": {
              "type": "Buffer",
              "data": "dyNg7uoQQfhZra4vgCOYpJuhBtPRMeFWAlDzIizo1Bk="
            }
          },
          "AvA8ZBCumaft6iQdemLTro9pvr+Dr01B0qq4KyRTK9w=": {
            "valueMac": {
              "type": "Buffer",
              "data": "acl02diVInAEgFBprOclQPCnyp+NszDjfa9s+ZpRcyk="
            }
          },
          "Av6EJ8l1c6Oedn+YNxPlPwotqoxwIOVzSrGrE3/2Adk=": {
            "valueMac": {
              "type": "Buffer",
              "data": "rLRkMjn0qwz57D2x/HPzP2+DFsqUU9g4SHmcBcbSBQY="
            }
          },
          "A0uFpshfPXvYYlvV97T4mpD5BPpYejFFGnY+nGcslkc=": {
            "valueMac": {
              "type": "Buffer",
              "data": "bbcof0NwgbAMBZY83rsbp+3PkYI6m4KN1fiwkKMWDDY="
            }
          },
          "CDKat4FVGx18E+EzaeoS4MQOWoFEKKEa3JfDOkk7Q3s=": {
            "valueMac": {
              "type": "Buffer",
              "data": "fcXcHaby6ZQQ8edi+fGIQLOjtopRsp+zS81cHk4yDrY="
            }
          },
          "CJJcDcO9dN/uOsN5NBkEtFdxxAclGNeZYl2Am6c8bO0=": {
            "valueMac": {
              "type": "Buffer",
              "data": "ZvOObVEsDoET3grLbyd4YhU/qIi9pt3ih7F4QDHumgE="
            }
          },
          "CpELLNq4/ia3A4vnTK7zQ7qiFS8ET3UTx9lLWeLnsTo=": {
            "valueMac": {
              "type": "Buffer",
              "data": "lltbNEmal3CVSYis92qUwNAowaBDQC0zS8O7ndje9n0="
            }
          },
          "EVEM9MtGQ5r7GBuZ5LayCt4OyFuB5lXdnS0yIVUCZnA=": {
            "valueMac": {
              "type": "Buffer",
              "data": "UcZTasKOnn+6r1KLhO7BnyVFMt520+I3QKK51F6qpRo="
            }
          },
          "ExCHSyQtIM9Cx80p0+9OTlBqdrV++qfVSa+rWCEHfYM=": {
            "valueMac": {
              "type": "Buffer",
              "data": "CUjQntJACq60SnB2JLLeIagtbUgKLvEKNxdJ6g4k6cA="
            }
          },
          "E+rUPgAc6GT+pCdBwex6MFBjxX4YJU5vl3rmSfFohHw=": {
            "valueMac": {
              "type": "Buffer",
              "data": "MakfMtu8wm2KnPT3rth+ZrsU2MQP2Yl622hGYx/8K6c="
            }
          },
          "FD8o05XqFUhy7Wu7PHPtHIaDC8zyhxZKr5Kjc9M2jNU=": {
            "valueMac": {
              "type": "Buffer",
              "data": "beCoFq+4UAdAu0xfFcq0+KvOW0+QPujHGhXOGJCMwbs="
            }
          },
          "F/OUVxSvEX289jp1wVziBoKZFta7lcI64h0Al0DlAFY=": {
            "valueMac": {
              "type": "Buffer",
              "data": "dNLDckGG5Dv7w4AKIUGKKZX0ioj8TcrQu8ZfeGS7xc8="
            }
          },
          "JFaWoYE685KGCMt6jd4sGmMGOIWeJzsvCkOBd65elEg=": {
            "valueMac": {
              "type": "Buffer",
              "data": "D3kIfGf9IyD2nN1CfQs3BHb52YLyuBIX0caoP68w/b4="
            }
          },
          "JQtVZGuH+CcqhBr+Zrmlhy3NevWzsG8L9CvUl7u3Z+4=": {
            "valueMac": {
              "type": "Buffer",
              "data": "A8SgJ3oP6y38TtriiSOYz1bkRPYWY7eXhjzT1BqtGHo="
            }
          },
          "JtoEAxbnjqwbq2xtLwOeasBiHCky8N65pnlAtLcV36E=": {
            "valueMac": {
              "type": "Buffer",
              "data": "N8eNUhRP1/EXLFVZj6lzc1WqM25ZeZIDkea+Ivu5jGw="
            }
          },
          "KvK3Mk8DbJDF2WH4oTaybZtVAL9DVpSBGlYtrzfroE0=": {
            "valueMac": {
              "type": "Buffer",
              "data": "VzmXxLG2NEncGWmqBehGTwcAxIn5qzJrfHEYu2/q080="
            }
          },
          "K5oTmPOH6duK5nF2hEVQ87mB8FxqYVItBj7qxV8CbXE=": {
            "valueMac": {
              "type": "Buffer",
              "data": "7jkSH5KLZQngienseT0q94SQkqAd93+yHRxtXnpEH0E="
            }
          },
          "LXK0kChcLyy0jKAq6Zs/2isDVpHGVXf98D1uguwzXHI=": {
            "valueMac": {
              "type": "Buffer",
              "data": "pNLVYnSLrtnJYEnVUi+XuIsIL0CXmmYlg5Ir1b0B6kE="
            }
          },
          "LykPiWVC/0kEuh4XhXzk6dkBQ7B7sshUkeJBPN7VhVA=": {
            "valueMac": {
              "type": "Buffer",
              "data": "z2v7D9RfijYq/r47lUOtXp+ajYd7SNdtcuFEKD2j6Rk="
            }
          },
          "NCaQ+33YL0EyLm7p47W8YhUNQmRbvG1auqJCqmGbLxw=": {
            "valueMac": {
              "type": "Buffer",
              "data": "wSxQQgdX2c/WX5pKRC7TVjBXcsXN/f6FnRV/ThSiWYs="
            }
          },
          "NyWmSLa6+lHhb52OxrRd1VR+Qs7+2CWk3NhXCVCSdj4=": {
            "valueMac": {
              "type": "Buffer",
              "data": "XSMT3ZrTETeRIsKLKP7uHe47w1OecAKDhbuTDVOrAww="
            }
          },
          "OIJd9zctO5ZpDAdFKju4TO0REgtq/YwteXcMaLSEWyQ=": {
            "valueMac": {
              "type": "Buffer",
              "data": "L12Tp0V/tTyJ9BEF2mnhskjJxtYKOskF8XuqfJ8UvUE="
            }
          },
          "O0spxhknjqt6st4gc635jw6sgxw2uDW/RGYGcbmSl8o=": {
            "valueMac": {
              "type": "Buffer",
              "data": "q2LVr+Tb4VoLaeuTFPuG0DZel4xUQ7H8VdCb61KDCEs="
            }
          },
          "PWiE2fcLr3W9xbjhLPqT6LEF4n+DzPdwg2ua1WVJPuk=": {
            "valueMac": {
              "type": "Buffer",
              "data": "b22gJfrz3GO+S/Nl6WYa4j7Fp2Q+3v+++lrxqZ35hic="
            }
          },
          "P3MCUV9k7Y1Fu++DUxleawigufvShQwkvXrQHmqkNeI=": {
            "valueMac": {
              "type": "Buffer",
              "data": "2RcUvVfMOu0hBPwSOIBDiZ9JycaA5vQhobK/h+OGMgA="
            }
          },
          "QEWCXjFK1twp04jJSN/b5XR3QZP44vmBYK3Cor5ZYu0=": {
            "valueMac": {
              "type": "Buffer",
              "data": "rrsPSaiGKfVKznnWbB8OOU9TthzGunDZq7VqozGwgLM="
            }
          },
          "QPBwbJ2Md6yhlfw3NnFwkBm42P4HRBeWKTMJeHd2NWg=": {
            "valueMac": {
              "type": "Buffer",
              "data": "W/HjOyVsvCS15DYh3Lth9eXe2XniBrN8NAQYJo3BbJM="
            }
          },
          "QcTWbVc4WKk+dP5C5MmTtkVmUqpcKwCGRyPHt0l+Hfo=": {
            "valueMac": {
              "type": "Buffer",
              "data": "rQEVqkssQNLC3zf0PPVPyynDSQ0QpZDcLNpGI5/uGhg="
            }
          },
          "Qlhex3VU8WrZLla5T7mu/9TyfN9NhxUWgnO1hRtM2XI=": {
            "valueMac": {
              "type": "Buffer",
              "data": "vQLTLKkLUmb2PB4qUcIYxHdS8Q/7MHPyN2uqerSYvMU="
            }
          },
          "R+HLuiE8kMBYuF9r379Fyc9Q3df1zFQqxPyI+ugSTyc=": {
            "valueMac": {
              "type": "Buffer",
              "data": "iPVE8UIW6OWRLTO7QCPOHZMo+K41X3SON4Tyt4O49Yc="
            }
          },
          "TX9ZX6l0RQ3RzeqlpMNuXbqZk976+YQXV9IW05woH0Y=": {
            "valueMac": {
              "type": "Buffer",
              "data": "Wj55WJNwNh2uXdiRjdyUNPlApGSu4IvKo1pD4vzZHH8="
            }
          },
          "UCbIUcaO/WuLOWWEz/jmYEZ0iN2LJhzrSdf34xPLAVo=": {
            "valueMac": {
              "type": "Buffer",
              "data": "RyJ7AzpMSsVEwLeq6yw9hDfgkEMMk+7dDakiH1C7mbg="
            }
          },
          "UZAzonH5/d7WVzlrFrpnLVaboJ+pwZrcueHJtmnMQPE=": {
            "valueMac": {
              "type": "Buffer",
              "data": "jbm5ShZSwybofnb4pcLnTNiUFhG1UPvayqMOCtEfqu4="
            }
          },
          "VIvMZZ0F0lhi59ijNAhHwMgUFiH06pYGyV5vesuask4=": {
            "valueMac": {
              "type": "Buffer",
              "data": "46tUnqn2qW1/VQXlLPPCrvETe/Gs8d8V0QLq83GY1ho="
            }
          },
          "V3XcCMooCQgJixj6O/pfBejhSa613K3kJyUYMtFR/Dc=": {
            "valueMac": {
              "type": "Buffer",
              "data": "cnTn8cj8kTuukWscqDfkKMvRozYp+STCywWcIqyz9mA="
            }
          },
          "V8Z7XOB4URq5m04prjS6QkRJ4rBXa2AhdJ2aGlZSE8g=": {
            "valueMac": {
              "type": "Buffer",
              "data": "UgW9T7SUATPXg/DBSkDiZWf915rmspYWPTaZxkh0CaA="
            }
          },
          "WP19/TRyClSkuFvx0Ez9I14Wy3vbJcQBcynHlpKozKY=": {
            "valueMac": {
              "type": "Buffer",
              "data": "zZO0pH98hnW4GJYRNFfdta6ol0Wt5pI0EYwawL9Bbk0="
            }
          },
          "WSqCKytRflXtWzdS/ZuMqh2MT8m6ELSxHmcAqrBPEWM=": {
            "valueMac": {
              "type": "Buffer",
              "data": "0Aqwzdiw/DLFZk38RrYJSHepJnTHMh0JP4n2E+qZrm8="
            }
          },
          "WUcXG1yIpaVYnmDZVPOs8mCVAEMGKzMBVpGjeDQu92A=": {
            "valueMac": {
              "type": "Buffer",
              "data": "Kwx5vgRCw0TkO/PnacxlZ48CJILjCVN3koSxtn+oy/s="
            }
          },
          "WVy/qfHpdBNg82HyFj7R/Uan+hNXQno9d6op+hXJtdA=": {
            "valueMac": {
              "type": "Buffer",
              "data": "S2UbnMVfPCDzzH/JcX4nZMWDC5L8sYYvBBKDLNDVAMk="
            }
          },
          "XIMIVZycTtRxzeTfR1U5CAd+RrVT/y8xeF5Ahkw+WjI=": {
            "valueMac": {
              "type": "Buffer",
              "data": "E2qADpLYzHl4YlmcS8KCnYkOp1VCogZ3Z8itt4SshPQ="
            }
          },
          "XLEkP+BSIj/13gaPhCHX20KoezmEchAa+qnMKx+tVdY=": {
            "valueMac": {
              "type": "Buffer",
              "data": "qCSQEF+hMCHKYuBCrLUEzDV6WT0aFkAq4ZIN6p4OqLA="
            }
          },
          "XShr/3cKOnkihLY/D9HHRDHZsZdM4PWUWYdjlXY2awI=": {
            "valueMac": {
              "type": "Buffer",
              "data": "omCrRVFDlrqcOwMTW/UKjLo/DMUrpYV2Fa+zAjDV1+Y="
            }
          },
          "Xarrth9UGuHJrU2T4w5gaklGUdvCzxpIooOPd/bvsVc=": {
            "valueMac": {
              "type": "Buffer",
              "data": "eXALPrMTJ59hy6EPCWykSV5375uaGpWUlzRjGe8/fQU="
            }
          },
          "YFwEKmVTr8XygR7/X0UA3/LBEdFYuwlb9mESSqdiJkQ=": {
            "valueMac": {
              "type": "Buffer",
              "data": "PQyaM8Zr/E4WQwb98ymMejRVBJbjySPjnvc7v39UPcE="
            }
          },
          "YNI8pZira2QwInzP6ASzGLK9MN4wDc0ehAPaoW3rh4k=": {
            "valueMac": {
              "type": "Buffer",
              "data": "d4eKptuwPWw5yERwlsNXt5LyntCRz6MgTh798oZq+QM="
            }
          },
          "YcV2EDPi+IRek33KLw04HShO+K2yCmPfLaUymfWKvBc=": {
            "valueMac": {
              "type": "Buffer",
              "data": "sDOpSGIYUjwEC2iEIhQKodBOicC4kD13eOIQuzrelJg="
            }
          },
          "ZNfLKCqYLU7ZPLVRQo/mqYDi6hWbC4FxazBxLbALp2Q=": {
            "valueMac": {
              "type": "Buffer",
              "data": "n2qEPZ8EYikILuKVwbONRGB/K7eEE2xhwZhN/3n8j+k="
            }
          },
          "aE9mA8RwtqjF6c06DFJuOJH6Sz5LFySIJ62r+M3Bbfg=": {
            "valueMac": {
              "type": "Buffer",
              "data": "MVzX153VKvU+oh1CTE64lhsDwhKGusQv994NputJo/Q="
            }
          },
          "aVMF3ZZO7R6bIuIL45xIhoRO8RYtpooI1+iDGudQP0I=": {
            "valueMac": {
              "type": "Buffer",
              "data": "8gYkXXxdFget6cOUb0GntjiFSdCa3lGGljQNAT3OFEA="
            }
          },
          "bvYMCZ9gv4s8iY2j/YWjI3BbhqW+PufAW4Gc8VwVgg4=": {
            "valueMac": {
              "type": "Buffer",
              "data": "EdJrTlfV1c7I9030uNs+xun8VG5Z6hb9VrnEDnb5rDE="
            }
          },
          "b7RDWmHE5vUotyHbMyZcpjWw97RLmxCYzssSOtIuYPw=": {
            "valueMac": {
              "type": "Buffer",
              "data": "gh9FAPeYPENEXtr6c6mt/JbHfMYUseC+Us0Ibuu6XBs="
            }
          },
          "b+bUjfFPpzuGK32NNSEdniXy/BRxp3UBZ4wLvvctjVY=": {
            "valueMac": {
              "type": "Buffer",
              "data": "mwO4XH0U5bLiYSqy6ThwTeb1zRH1kiYIUE1v5s+aF+8="
            }
          },
          "dcDg59+mKfjAEOOycuvhxjgI8ABTgRhKOzmMbyH4rrw=": {
            "valueMac": {
              "type": "Buffer",
              "data": "BodGeUrXq37gXaSW+4kGqK1SKoZ+XZxXikxpyrP3XwM="
            }
          },
          "eTtk9kfMm5WQjvFzeGet9v/HR6/np4zQRWUqNdsG12s=": {
            "valueMac": {
              "type": "Buffer",
              "data": "fvg/iQHCGqepC8y9sNqxfAXXIAIHO4uZjxI3QF01fd4="
            }
          },
          "eVMaYTVCZmdGaV/B1/yJKLD97dRlcBdq9e26E4VZyiQ=": {
            "valueMac": {
              "type": "Buffer",
              "data": "snigetSa0LbM24X83E9xo8WSylXJoZVyagvZx7ldwsM="
            }
          },
          "fqbJIQZJtgp+TouK8mRuoLpxj6BqgaMe0aU4x+3IBbg=": {
            "valueMac": {
              "type": "Buffer",
              "data": "ZP76qAk+Ro4TaTj0LXPQz0/dUuXxPfUL+F7yuc5D/Zs="
            }
          },
          "gfA9Ypsy7J883XoxWKPv/NDm2sCJP+g7Tavex/uTGYc=": {
            "valueMac": {
              "type": "Buffer",
              "data": "znKA7F+uoRLqQaQVp/6GD4TawXmLPWjMYTfmaRn06zE="
            }
          },
          "g98FSYu8W0CMP6HmTKSWJBi+VlYQdX6PKq/jBKT+Zao=": {
            "valueMac": {
              "type": "Buffer",
              "data": "YpoS/vISASAh6dhx9Um11/cgBOOQQBsLOpAXld81WnY="
            }
          },
          "hc2nVNR9HgxiNT7Vi3stVWQdIpY9MrULYMsmWsoQTCs=": {
            "valueMac": {
              "type": "Buffer",
              "data": "ukGA5n1Ggj3s16nMq3uXFrUCJYlfQcJUpulD12ba3WY="
            }
          },
          "hiiquv2bG3c236sd6QpD4PcgqsEl+QvhNIXA4/zV9UQ=": {
            "valueMac": {
              "type": "Buffer",
              "data": "E5Rtd03aKC4o5uuSdvfwefoqCuFfL+OpqkhJhMBAHQc="
            }
          },
          "h9pvcIkY9CrHaoBW2DZOVvnwstE/z1+NCPZuMzkSfq4=": {
            "valueMac": {
              "type": "Buffer",
              "data": "4VFAtrXRZbw4+cMj48Wl6DXF0m1EBNtG1Ke/9i6wd70="
            }
          },
          "iNYW6YExdxABcdyLBkrmkiGbx1NL4rXrdmZeBLjL8uQ=": {
            "valueMac": {
              "type": "Buffer",
              "data": "m+NFA1TzzIGMPqSrd8Y49f8BuilChnLWSOlCPre+Zaw="
            }
          },
          "if8L2ULl6dgDk1CMNrpc8IiqkbWHulYOTf5J0WzV1jo=": {
            "valueMac": {
              "type": "Buffer",
              "data": "WboWuAVUYSRw0suAEeFdDmYSBTTI1ewlbmRw0JF1QsE="
            }
          },
          "j21ElJXPfu/co+MVN7Ct6DDPiVrJCr64X96KGu6TqCg=": {
            "valueMac": {
              "type": "Buffer",
              "data": "JFJZ2+yAlJkUs96ugXD5jn+NorEVjppPTPvw7bjm8tY="
            }
          },
          "j38FHNnPhMPr8j4lUcWWUrwE+vim4xkf5s1uMFoaLmc=": {
            "valueMac": {
              "type": "Buffer",
              "data": "TVdCfBNXKGe8TSKoIwqJnvY+9kERU5lHm37nSJ5XQRo="
            }
          },
          "kv9Qoz3duP5eLSWRz9qKHzOiOQ4NHFg19Ea1Xpemjho=": {
            "valueMac": {
              "type": "Buffer",
              "data": "lga9xiPjUKjIildkaI5O8kr1Ht2rZXp71fjX+6tL++Q="
            }
          },
          "lHfd/jj6oqmjh7JPgZcBfIeHzAkW1EXFyybi91hE9Ww=": {
            "valueMac": {
              "type": "Buffer",
              "data": "Xk2zocywQEikUQ1ng+g4COdd72OevJ440pyJKA5xTYg="
            }
          },
          "l2rotP8WQuOkgfzykPS/Y2IiFq/PviAc2tPFb+SVY6Y=": {
            "valueMac": {
              "type": "Buffer",
              "data": "IDNiba4vxgY1767f8Ezp/QeYXgreHJxCUmxqQ2ekMrM="
            }
          },
          "mpiptMPa17iMjBv2Tiqnok1lWv4hoHT41KKpf9dISuY=": {
            "valueMac": {
              "type": "Buffer",
              "data": "2jNl2r/7ZeRQcWpqEUjoPCRZJXTbVu+iIOL9lhssoQw="
            }
          },
          "mswbVXkejEqIKd//xPbyAr/P1UjuG5CRGBTZ5bBZLrI=": {
            "valueMac": {
              "type": "Buffer",
              "data": "Ly9gOIOGgg9VUfC5am7sblKcxubZvztPU23tcAGpBoQ="
            }
          },
          "nmEwHpjEA67WbKT6moLKMrOKZZ0Gaqfi/mj4zIej4z8=": {
            "valueMac": {
              "type": "Buffer",
              "data": "bMvi9XAjj5GkAa90WM5mEauGN629zHIV1iIsRX3RCik="
            }
          },
          "nslFy8fpUhwdPANepXpSVFaU88SsKGIT+RMA3V6t3ws=": {
            "valueMac": {
              "type": "Buffer",
              "data": "akHBM7cjM+yGEkw5TAPkhwl68MTj7PGpPaMY5xdnFdk="
            }
          },
          "oO/aNo/QKiqN0TEWmI1MvXwJstwOzzv8NrShLjAep4g=": {
            "valueMac": {
              "type": "Buffer",
              "data": "ncPBV1h0p00hjqrvOw+McP4JkJ7HobjQngJoqvVEfXo="
            }
          },
          "pGto882sZiCKP3o7ct7qftsNpoBkoE2r1+whAshvqcs=": {
            "valueMac": {
              "type": "Buffer",
              "data": "RbC3IQ3siAn2SuUhAz8S2xGoLehBY7F79bAN+ziWLlI="
            }
          },
          "pPq4Sk0LZ9vr3nsU+MqoSCAPc7XLzcegAtWkjVvfuLc=": {
            "valueMac": {
              "type": "Buffer",
              "data": "OvoNm2HuqWoQ5iR2H5ZtP1UeVUF6xzN3j7SYnIMselI="
            }
          },
          "plbBYaHjuZ9aE8h9lDk/tSTX8EKJzOE4LvLzvQx8iw4=": {
            "valueMac": {
              "type": "Buffer",
              "data": "C3SrANS+EOI1prUW7JvQaq9/XxGUoiIC4/6WJD+Jo48="
            }
          },
          "qHj4wZpxMOptjA730uizipuIErfHJu38TXJIXIM0j8s=": {
            "valueMac": {
              "type": "Buffer",
              "data": "ln/ojUw+xhIU9HR80fn+P84Qjcu+odYyy1IQCaQU/eQ="
            }
          },
          "qmiQ4ATjJPvsjOAltgt014zgYFQwvbfx+p9flKWXdUM=": {
            "valueMac": {
              "type": "Buffer",
              "data": "EYUkdj9AF/1hGP+PM7wDv3inNY9GPpmBrPCbEdbrnZA="
            }
          },
          "quj+GxyzDKzMk5n6XIBCs4RkWmY7RoF1XcKBLM7nG4A=": {
            "valueMac": {
              "type": "Buffer",
              "data": "JH3mRBsoh38vIRdTuPK3++IrRLds3ySExSgINXq5wr8="
            }
          },
          "rIKAgXGGrwGFxifEk8YRcxUc5wbV4bKmno8VvDRmRis=": {
            "valueMac": {
              "type": "Buffer",
              "data": "DXluyNLthHxYVQ/vrteHE0KGuq77XCDjhHdvx/Oc1Cc="
            }
          },
          "rxMu054aDuZXyv0VInDy7E9gnvDgxP9EI0vi8Ukx/yg=": {
            "valueMac": {
              "type": "Buffer",
              "data": "5yx9RHwFOZc/Qo48XO7F62Dpb8x3y83LSLPstx7q6pI="
            }
          },
          "sodfabzfOfIfo57WpRE23jW+DgN/28J9URfByqMLQ8Q=": {
            "valueMac": {
              "type": "Buffer",
              "data": "2T7WlnRNRza8K2y0WF51z7sHjjBPcyCL5IWBDvAAtCc="
            }
          },
          "tOBL0txqf+JD4PMTkNrwDoq4SPm7rqK/4HlbMK68Rtk=": {
            "valueMac": {
              "type": "Buffer",
              "data": "xOfJ4hrCvLt3KWMiwv+eNlRI2SDXluA4mO/lSvo6PVI="
            }
          },
          "t2GLW4VO+5jGyPezZYJr8eQ+6dpFQaitAulDyO8YEdY=": {
            "valueMac": {
              "type": "Buffer",
              "data": "bhnNJkw/1iOYeF+75t4GJSvwSkOzbKeJPqMJR+I+kVA="
            }
          },
          "t6ZAoieuZxNEIHpR4MTtFU4bLk/IiHXozmWiAov7pG4=": {
            "valueMac": {
              "type": "Buffer",
              "data": "Pa/CgH0ILEsekNdUAB9zWr7HSK7RQ8HtpwEKIKcIiF4="
            }
          },
          "t+1QSUZLfoV+eI6l2SUJteVG8hSFaWCqqOFHhOKcxsk=": {
            "valueMac": {
              "type": "Buffer",
              "data": "0sHMCL5J49QKPAnaSw6kB5N73jaS4wiv31RqHV2EPvY="
            }
          },
          "ulbF5oGy9/izGUaZrRWbDjJ41X3MZohtlxSxwpMZ5VQ=": {
            "valueMac": {
              "type": "Buffer",
              "data": "1WOWnj7G6YcTspegmckmMqEX1iVPiEVP7a7Wj4DhoWU="
            }
          },
          "u2cwZEOKf/QT/969Al5bleoqAb6SaQgqVAGWv8WKXhA=": {
            "valueMac": {
              "type": "Buffer",
              "data": "aHXTml3hM6gdKFDoLuzaM0pgsNKYG4Wk7CiZWQXVq04="
            }
          },
          "vu7/1a7/w1swpuukQxfwDSf5/YtxQkbXgUF06+DFY6w=": {
            "valueMac": {
              "type": "Buffer",
              "data": "ejeQf5ZkAPIhxXbg2qjUEMkUaA9P0YXFJ7NckIuRO/o="
            }
          },
          "vvj3uJ/ZX2IorFD8+gOvKY5pKFvtKa5xxCHnJSXQh78=": {
            "valueMac": {
              "type": "Buffer",
              "data": "rRanAk6Q0cVWMjvRJJBEDKz9TlkPWmIyuFxGArJN+18="
            }
          },
          "wK7Z71EvTGLund93Kk4D7vOxbLINBi9YgJy2J+5GKlk=": {
            "valueMac": {
              "type": "Buffer",
              "data": "0OeDhH19cpOSA+y/TCMzWvuJk1gxmcaOvJyPwuVv4xI="
            }
          },
          "wXJhSFZUR1hIKxRrDEk3P7+FDUsX+32ihviX9Rgti78=": {
            "valueMac": {
              "type": "Buffer",
              "data": "7p38nV3S8MFWk395U7ARZkG1xPHbPfHPVx2sZKRGO4Q="
            }
          },
          "wtoAJ59CLbuOc1RnVdkQ1om0o70Hdy9vn04VEHHYOPM=": {
            "valueMac": {
              "type": "Buffer",
              "data": "VqKET5X5ErSD1zF1FL474JXF3470K69KyVGNKbgEWAw="
            }
          },
          "xV3alKj/RCfm16y+VoVifP9OjbV1Vmg0qAhOy8zfvVk=": {
            "valueMac": {
              "type": "Buffer",
              "data": "WWhdr3/HabErfqLoNloRlobk2ZoYPGjMfOw1rjufDl0="
            }
          },
          "xzsQSJs7VUsY7M/X7UgtQEgou1z0HyQ2g8jQpjD+eA4=": {
            "valueMac": {
              "type": "Buffer",
              "data": "XdKFji/CgFOGpTPBsDm/scB0iIMy/weHrGtSwCwSskE="
            }
          },
          "x1chq7awvO6F8K4pPLpG/AIMlIdUDMuXlcSbk7jfPok=": {
            "valueMac": {
              "type": "Buffer",
              "data": "Bx9SKoTyU4QJNBpwuI0XFXJHuuATCtMhksoFBUwufTE="
            }
          },
          "ysICo6SSgGhEsRuEUP/ESgB1ql1xLAOvAD5f+xvd/h0=": {
            "valueMac": {
              "type": "Buffer",
              "data": "LH0fRGDkKHWMpdXLIexhobbAtR3f4UHcMIMrMDFTeak="
            }
          },
          "yulQPmcvr5YOx+breLXUeMTL0rkGWWVTOL2WSRMYxrE=": {
            "valueMac": {
              "type": "Buffer",
              "data": "BbHHZPhDDciiuX0nGs7ijWGEe/oYavlurI0t4DpLtow="
            }
          },
          "zRS4O7vXzghSdGUvXn3tZGhe4/SdgizRQ99OQNcE/0g=": {
            "valueMac": {
              "type": "Buffer",
              "data": "aIIBX+ZJihaxwYwoQkkRQ9w1mmhaExJ25hkhCDlqqFs="
            }
          },
          "z9QjuWPbdkzmHFh6Mg1hmn1BKk/hGL8KA4uhwrdWAoY=": {
            "valueMac": {
              "type": "Buffer",
              "data": "p4l2/s1CA5x8cIrO+oPaVwx5O4diX9/I9WkrXFxlVME="
            }
          },
          "0bffHhW8hJAqgnNnPdtvwZn4p/g/mZ61sC8yBzhhNQ4=": {
            "valueMac": {
              "type": "Buffer",
              "data": "gna9tZLSyHf1PcIs8UbZ6XI4401Ah9lAcEKVYUkGLmY="
            }
          },
          "1Pha22Gao4MAmUO8KUUy/EKF3vGbLAS1/Y2yEap2JbE=": {
            "valueMac": {
              "type": "Buffer",
              "data": "m563Ke8T3T0WvUPOjtEzwYc0Rb4ZWUm+2lnHVV8HCtg="
            }
          },
          "3VdIpo4wEYD/nJ+y3+PttDBjOuDcTgndcA/WaiY5WTs=": {
            "valueMac": {
              "type": "Buffer",
              "data": "fr0XnXJaRdFDUsQEywcxPVXhfOvVRkbBngZIjXvwvxY="
            }
          },
          "37g40bcV4aCA6P2nlyyAv2iBm2eIO2GXDNmYRp6SV3s=": {
            "valueMac": {
              "type": "Buffer",
              "data": "Tk3ON6mwFT4UFBo/J4C6woy179jf+4tdtav5uU+zOko="
            }
          },
          "4K99WyrpSR2qjBCF3ldFUpIrw7tlxnsWpVIcSPMh76k=": {
            "valueMac": {
              "type": "Buffer",
              "data": "/FzZiaHN+esq6Wg58pqGeQ7ghmVzj95x3T+yNsgS5ns="
            }
          },
          "43lIpVT4KjK+h5n402TP0rJD9JT/oCeOZ5gZ2DzmgPU=": {
            "valueMac": {
              "type": "Buffer",
              "data": "QVXvtIjMHWP38oD8MpA48Lqklzp7qJuuXEExBtRNHJk="
            }
          },
          "4/VwELtMiy7lFNriwnz83ehbVVSQMsOw1+aE3ytLazs=": {
            "valueMac": {
              "type": "Buffer",
              "data": "xbUGzRzADss74JugpfrlHyLEghN1EURBchQGEIGqTyI="
            }
          },
          "57JBa0OYlUynueRndA9E+AK8ZXDbQbScGP2DNrnEQKM=": {
            "valueMac": {
              "type": "Buffer",
              "data": "gdw57y3elijTTisa7eUyo5s7SAInNc+xPnvAgluONas="
            }
          },
          "6BCsIq3/biYgaoUyoZC4zAxTig0PjOchcMQYoeOzuLw=": {
            "valueMac": {
              "type": "Buffer",
              "data": "topPs8AV/rn/SIfZOSKDyWiU/7aiGK0/KrtknlGmpiQ="
            }
          },
          "7c6EcSJkfzLbh3BVd8J3UPDzbt2fgDhlPzCu4qK8C9k=": {
            "valueMac": {
              "type": "Buffer",
              "data": "FEMnt6OI6CL3mj+B68Kkrf+nBDdU1V6flEUDQ4Ia8gw="
            }
          },
          "7l9UyoRAFRumljCQBvkScixA2dIiNJJD8hv0uisxgdk=": {
            "valueMac": {
              "type": "Buffer",
              "data": "IMSLYOZthiKHT3k9Bgm5bNIjxJsuiSjE9fREWzXttcc="
            }
          },
          "7wh+VxOei6dS3ERXPfRUeyKdl0HSpBCnm2mei2p2X6A=": {
            "valueMac": {
              "type": "Buffer",
              "data": "kmv5O957hqsw7SYN7PY7xpNOqkoFojBNH2hDJ2tKqdo="
            }
          },
          "76Kbide/Sr7STMYCen2wzH3mvwnnhLnlakLzIxp2SOw=": {
            "valueMac": {
              "type": "Buffer",
              "data": "KqiHY9DvtJZPK6LntZzPK92J0KUZsNkLMMrYsIXZrWY="
            }
          },
          "99gCjqV8/qRh+piPGyDwqr73pOSdQqNDZNTx+dO++2A=": {
            "valueMac": {
              "type": "Buffer",
              "data": "vLZBwU4xmvmZUDt6nSguq9RRiteU17RjM9wHgtJFddk="
            }
          },
          "+99x30r+JxcJ7ouoWu8q6sDTryjGeuTugSKwHpfyT9A=": {
            "valueMac": {
              "type": "Buffer",
              "data": "vYpbn/YkEKgJYRRD3Es0GQMuP2OnAGpHDBsLNJ08Wh0="
            }
          },
          "+/N3FqnNIWQPVgP9qKMKRYj/7hVANpQGLoyt2AiPvpA=": {
            "valueMac": {
              "type": "Buffer",
              "data": "YFYUWnYLP1DHcbIi+hhQkuuHxMfdxSn2ba4t6MGkQZo="
            }
          },
          "/9vqPPJwzbv97BwXhi6SYY7G8xmtoytxHWT1ftBwV78=": {
            "valueMac": {
              "type": "Buffer",
              "data": "XB+zS0qJhiDS1s2191HRqrMnyvUgOcYM/U+loeDEP/4="
            }
          }
        }
      },
      "regular_high": {
        "version": 5,
        "hash": {
          "type": "Buffer",
          "data": "j55UGfpYgUYhWXqPDuQK1i5pz6XTGeb2gpEAELk26+Lwoq4aWIUPizwptSrFco2omJFpmIonijFeyl8Sd4FAA6q9W/8t7sD4xNXmn8N/Pu/uPY7Uk2t5v9t5MAA3YJNZxZzp/mQbKZ52blvktSDp6TMhFpw3ZsYb2+tnNr+2Kys="
        },
        "indexValueMap": {
          "If6sbNaw83rZ7PFJNu7Yoig2JWUIpqT4l2xUL405qXo=": {
            "valueMac": {
              "type": "Buffer",
              "data": "XRt+ok5Ch4Otzf7nhLWeTZGw1p5ssUcGUPWXlCmJKfk="
            }
          },
          "np16omE9vmAnyLFzRMGbh1Md1RDuyzYqGoQaC4PqxEY=": {
            "valueMac": {
              "type": "Buffer",
              "data": "q02fAduZq8bpk52d6+sNsr8aH1jaxo2+RKOjUb8MZIE="
            }
          },
          "tK7pmuUC2iCz+3mM30GfBHyej6ql0ovEeZH+dslMecw=": {
            "valueMac": {
              "type": "Buffer",
              "data": "EyBzOwHHtz53v92oji3aUksb+3H7/AgXcGq/4ziuaNc="
            }
          },
          "sERGMir+2UWHL6bByLAugJsMOWSxCFgjqhYxiYYyg58=": {
            "valueMac": {
              "type": "Buffer",
              "data": "MZZtAZZwEt9NnCIM8zzemWYgpBCT5moc8isdNOugyY8="
            }
          },
          "fAHBO4wUV7+HuDm3Ckb0iADbcysSAt1/IcPKY/K9JAQ=": {
            "valueMac": {
              "type": "Buffer",
              "data": "41kx/ljFHgeMnOCvQlx6dkuRn7U+XxxhTMAVPWnqcoU="
            }
          }
        }
      }
    }
  }
}
